openspeleo_core-0.0.4.dist-info/METADATA
openspeleo_core-0.0.4.dist-info/WHEEL
openspeleo_core-0.0.4.dist-info/entry_points.txt
openspeleo_core-0.0.4.dist-info/licenses/LICENSE
openspeleo_core.libs/libgcc_s-80f55268.so.1
openspeleo_core/__init__.py
openspeleo_core/_rust_lib.cpython-313-powerpc64le-linux-musl.so
openspeleo_core/_rust_lib/ariane.pyi
openspeleo_core/_rust_lib/mapping.pyi
openspeleo_core/ariane_core/__init__.py
openspeleo_core/commands/__init__.py
openspeleo_core/commands/convert.py
openspeleo_core/commands/main.py
openspeleo_core/compass_core/__init__.py
openspeleo_core/legacy/__init__.py
openspeleo_core/legacy/processing.py
openspeleo_core/legacy/xml_utils.py
openspeleo_core/mapping.py
openspeleo_core-0.0.4.dist-info/RECORD
