Metadata-Version: 2.4
Name: openspeleo_core
Version: 0.0.4
Classifier: Development Status :: 5 - Production/Stable
Classifier: Intended Audience :: Developers
Classifier: Intended Audience :: Education
Classifier: Intended Audience :: Science/Research
Classifier: Programming Language :: Rust
Classifier: Programming Language :: Python :: 3 :: Only
Classifier: Programming Language :: Python :: Implementation :: CPython
Requires-Dist: lxml>=6.0,<7.0 ; extra == 'legacy'
Requires-Dist: dicttoxml2>=2.1,<2.2 ; extra == 'legacy'
Requires-Dist: xmltodict>=1.0,<1.1 ; extra == 'legacy'
Requires-Dist: deepdiff>=7.0,<9.0 ; extra == 'benchmark'
Requires-Dist: scipy>=1.15.0,<2.0.0 ; extra == 'benchmark'
Requires-Dist: xmltodict>=1.0,<1.1 ; extra == 'benchmark'
Requires-Dist: deepdiff>=7.0,<9.0 ; extra == 'test'
Requires-Dist: hypothesis>=6.128,<6.141 ; extra == 'test'
Requires-Dist: pytest>=8.0.0,<9.0.0 ; extra == 'test'
Requires-Dist: pytest-cov>=5.0.0,<8.0.0 ; extra == 'test'
Requires-Dist: pytest-dotenv>=0.5.0,<1.0.0 ; extra == 'test'
Requires-Dist: pytest-env>=1.1.3,<2.0.0 ; extra == 'test'
Requires-Dist: pytest-runner>=6.0.0,<7.0.0 ; extra == 'test'
Requires-Dist: pytest-ordering>=0.6,<1.0.0 ; extra == 'test'
Requires-Dist: parameterized>=0.9.0,<0.10 ; extra == 'test'
Provides-Extra: legacy
Provides-Extra: benchmark
Provides-Extra: test
License-File: LICENSE
Author-email: Jonathan Dekhtiar <jonathan@dekhtiar.com>
Requires-Python: >=3.10
